env2str/__init__.py
env2str/env2str.py
env2str-0.1.0.dist-info/METADATA
env2str-0.1.0.dist-info/WHEEL
env2str-0.1.0.dist-info/entry_points.txt
env2str-0.1.0.dist-info/RECORD
