Metadata-Version: 2.1
Name: env2str
Version: 0.1.0
Summary: 
Author: dbessey
Author-email: daniel.bessey@unistra.fr
Requires-Python: >=3.12,<4.0
Classifier: Programming Language :: Python :: 3
Classifier: Programming Language :: Python :: 3.12
Requires-Dist: python-dotenv (>=1.0.1,<2.0.0)
Requires-Dist: typer (>=0.12.3,<0.13.0)
